traits-stubs/__init__.pyi
traits-stubs/api.pyi
traits-stubs/base_trait_handler.pyi
traits-stubs/constants.pyi
traits-stubs/ctrait.pyi
traits-stubs/ctraits.pyi
traits-stubs/editor_factories.pyi
traits-stubs/has_traits.pyi
traits-stubs/trait_handler.pyi
traits-stubs/trait_handlers.pyi
traits-stubs/trait_numeric.pyi
traits-stubs/trait_type.pyi
traits-stubs/trait_types.pyi
traits-stubs/traits.pyi
traits_stubs_tests/__init__.py
traits_stubs_tests/test_all.py
traits_stubs_tests/util.py
traits_stubs_tests/examples/Any.py
traits_stubs_tests/examples/BaseClass.py
traits_stubs_tests/examples/Bool.py
traits_stubs_tests/examples/CInt.py
traits_stubs_tests/examples/Callable.py
traits_stubs_tests/examples/Complex.py
traits_stubs_tests/examples/Date.py
traits_stubs_tests/examples/Datetime.py
traits_stubs_tests/examples/Dict.py
traits_stubs_tests/examples/DictStrAny.py
traits_stubs_tests/examples/DictStrFloat.py
traits_stubs_tests/examples/DictStrInt.py
traits_stubs_tests/examples/Enum.py
traits_stubs_tests/examples/File.py
traits_stubs_tests/examples/Float.py
traits_stubs_tests/examples/HasStrictTraits.py
traits_stubs_tests/examples/HasTraits.py
traits_stubs_tests/examples/Instance.py
traits_stubs_tests/examples/Int.py
traits_stubs_tests/examples/Interface.py
traits_stubs_tests/examples/List.py
traits_stubs_tests/examples/ListBool.py
traits_stubs_tests/examples/ListComplex.py
traits_stubs_tests/examples/ListFloat.py
traits_stubs_tests/examples/ListInt.py
traits_stubs_tests/examples/Map.py
traits_stubs_tests/examples/PrefixList.py
traits_stubs_tests/examples/PrefixMap.py
traits_stubs_tests/examples/Property.py
traits_stubs_tests/examples/Range.py
traits_stubs_tests/examples/Set.py
traits_stubs_tests/examples/Str.py
traits_stubs_tests/examples/String.py
traits_stubs_tests/examples/Time.py
traits_stubs_tests/examples/TraitDict.py
traits_stubs_tests/examples/Tuple.py
traits_stubs_tests/examples/UUID.py
traits_stubs_tests/examples/WeakRef.py
traits_stubs_tests/examples/completeness.py
traits_stubs-6.4.0.dist-info/LICENSE.txt
traits_stubs-6.4.0.dist-info/METADATA
traits_stubs-6.4.0.dist-info/WHEEL
traits_stubs-6.4.0.dist-info/top_level.txt
traits_stubs-6.4.0.dist-info/RECORD
