Metadata-Version: 2.1
Name: traits-stubs
Version: 6.4.0
Summary: Type annotations for the Traits package
Home-page: https://github.com/enthought/traits
Download-URL: https://pypi.python.org/pypi/traits-stubs
Author: Enthought
Author-email: info@enthought.com
License: BSD
Classifier: Development Status :: 4 - Beta
Classifier: Intended Audience :: Developers
Classifier: Intended Audience :: Science/Research
Classifier: License :: OSI Approved :: BSD License
Classifier: Operating System :: MacOS :: MacOS X
Classifier: Operating System :: Microsoft :: Windows
Classifier: Operating System :: POSIX :: Linux
Classifier: Programming Language :: Python
Classifier: Programming Language :: Python :: 3
Classifier: Programming Language :: Python :: 3.6
Classifier: Programming Language :: Python :: 3.7
Classifier: Programming Language :: Python :: 3.8
Classifier: Programming Language :: Python :: 3.9
Classifier: Programming Language :: Python :: 3.10
Classifier: Programming Language :: Python :: 3.11
Classifier: Programming Language :: Python :: Implementation :: CPython
Classifier: Topic :: Scientific/Engineering
Classifier: Topic :: Software Development
Classifier: Topic :: Software Development :: Libraries
Classifier: Topic :: Software Development :: User Interfaces
Classifier: Typing :: Typed
Requires-Python: >=3.6
License-File: LICENSE.txt
Requires-Dist: traits
Requires-Dist: typing-extensions ; python_version < "3.8"
Provides-Extra: test
Requires-Dist: mypy ; extra == 'test'
